mathactive/__init__.py
mathactive/data/difficulty_start_stop_step.csv
mathactive/data/difficulty_start_stop_step_revised.csv
mathactive/generators.py
mathactive/hints.py
mathactive/machine.py
mathactive/manage.py
mathactive/microlessons/num_one.py
mathactive/microlessons/utils.py
mathactive/personalize.py
mathactive/python_quiz.py
mathactive/questions.py
mathactive/utils.py
mathactive/webapp/__init__.py
mathactive/webapp/admin.py
mathactive/webapp/apps.py
mathactive/webapp/migrations/__init__.py
mathactive/webapp/models.py
mathactive/webapp/tests.py
mathactive/webapp/views.py
mathactive/website/__init__.py
mathactive/website/asgi.py
mathactive/website/settings.py
mathactive/website/urls.py
mathactive/website/wsgi.py
mathactive-0.0.14.dist-info/LICENSE.md
mathactive-0.0.14.dist-info/METADATA
mathactive-0.0.14.dist-info/WHEEL
mathactive-0.0.14.dist-info/RECORD
