Metadata-Version: 2.1
Name: mathactive
Version: 0.0.14
Summary: Conversational math active learning.
License: AGPLv3
Author: hobs
Author-email: hobson@totalgood.com
Classifier: License :: Other/Proprietary License
Classifier: Programming Language :: Python :: 2
Classifier: Programming Language :: Python :: 2.7
Classifier: Programming Language :: Python :: 3
Classifier: Programming Language :: Python :: 3.4
Classifier: Programming Language :: Python :: 3.5
Classifier: Programming Language :: Python :: 3.6
Classifier: Programming Language :: Python :: 3.7
Classifier: Programming Language :: Python :: 3.8
Classifier: Programming Language :: Python :: 3.9
Classifier: Programming Language :: Python :: 3.10
Classifier: Programming Language :: Python :: 3.11
Requires-Dist: django (==4.2.1)
Requires-Dist: fastapi (==0.95.2)
Requires-Dist: mathtext (>=0.0.14)
Requires-Dist: python-statemachine
Requires-Dist: toml
